cjm_fasthtml_media_gallery/__init__.py
cjm_fasthtml_media_gallery/_modidx.py
cjm_fasthtml_media_gallery/components/__init__.py
cjm_fasthtml_media_gallery/components/controls.py
cjm_fasthtml_media_gallery/components/gallery.py
cjm_fasthtml_media_gallery/components/grid_view.py
cjm_fasthtml_media_gallery/components/list_view.py
cjm_fasthtml_media_gallery/components/players.py
cjm_fasthtml_media_gallery/components/preview.py
cjm_fasthtml_media_gallery/core/__init__.py
cjm_fasthtml_media_gallery/core/config.py
cjm_fasthtml_media_gallery/core/html_ids.py
cjm_fasthtml_media_gallery/core/icons.py
cjm_fasthtml_media_gallery/patterns/__init__.py
cjm_fasthtml_media_gallery/patterns/pagination.py
cjm_fasthtml_media_gallery/routes/__init__.py
cjm_fasthtml_media_gallery/routes/handlers.py
cjm_fasthtml_media_gallery/serving/__init__.py
cjm_fasthtml_media_gallery/serving/mounter.py
cjm_fasthtml_media_gallery-0.0.1.dist-info/licenses/LICENSE
cjm_fasthtml_media_gallery-0.0.1.dist-info/METADATA
cjm_fasthtml_media_gallery-0.0.1.dist-info/WHEEL
cjm_fasthtml_media_gallery-0.0.1.dist-info/entry_points.txt
cjm_fasthtml_media_gallery-0.0.1.dist-info/top_level.txt
cjm_fasthtml_media_gallery-0.0.1.dist-info/RECORD
